mammoth_commons/__init__.py
mammoth_commons/custom_kfp.py
mammoth_commons/externals.py
mammoth_commons/integration.py
mammoth_commons/integration_callback.py
mammoth_commons/reminders.py
mammoth_commons/testing.py
mammoth_commons/datasets/__init__.py
mammoth_commons/datasets/csv.py
mammoth_commons/datasets/dataset.py
mammoth_commons/datasets/graph.py
mammoth_commons/datasets/graph_csh.py
mammoth_commons/datasets/image.py
mammoth_commons/datasets/image_pairs.py
mammoth_commons/datasets/text.py
mammoth_commons/datasets/backend/__init__.py
mammoth_commons/datasets/backend/onnx_implementations.py
mammoth_commons/datasets/backend/onnx_transforms.py
mammoth_commons/datasets/backend/torch_implementations.py
mammoth_commons/exports/HTML.py
mammoth_commons/exports/__init__.py
mammoth_commons/exports/markdown.py
mammoth_commons/models/__init__.py
mammoth_commons/models/empty.py
mammoth_commons/models/llm.py
mammoth_commons/models/model.py
mammoth_commons/models/node_ranking.py
mammoth_commons/models/onnx.py
mammoth_commons/models/onnx_ensemble.py
mammoth_commons/models/predictor.py
mammoth_commons/models/pytorch.py
mammoth_commons/models/pytorch2onnx.py
mammoth_commons/models/researcher_ranking.py
mammoth_commons/models/trivial.py
mammoth_commons-0.1.25.dist-info/licenses/LICENSE
mammoth_commons-0.1.25.dist-info/METADATA
mammoth_commons-0.1.25.dist-info/WHEEL
mammoth_commons-0.1.25.dist-info/top_level.txt
mammoth_commons-0.1.25.dist-info/RECORD
