Metadata-Version: 2.4
Name: MAMMOth-commons
Version: 0.1.25
Summary: Component interfaces of the MAI-BIAS toolkit.
Home-page: https://github.com/mammoth-eu/mammoth-commons
Author: Emmanouil (Manios) Krasanakis
Author-email: maniospas@hotmail.com
Classifier: Programming Language :: Python :: 3
Classifier: Operating System :: OS Independent
License-File: LICENSE
Requires-Dist: numpy>=2.0.0
Requires-Dist: markdown2
Requires-Dist: dill
Provides-Extra: deployment
Requires-Dist: numpy>=2.0.0; extra == "deployment"
Requires-Dist: markdown2; extra == "deployment"
Requires-Dist: dill; extra == "deployment"
Dynamic: author
Dynamic: author-email
Dynamic: classifier
Dynamic: description
Dynamic: description-content-type
Dynamic: home-page
Dynamic: license-file
Dynamic: provides-extra
Dynamic: requires-dist
Dynamic: summary
